claudebook/__init__.py
claudebook/py.typed
claudebook-0.1.3.dist-info/METADATA
claudebook-0.1.3.dist-info/WHEEL
claudebook-0.1.3.dist-info/entry_points.txt
claudebook-0.1.3.dist-info/licenses/LICENSE
claudebook-0.1.3.dist-info/RECORD
