Metadata-Version: 2.4
Name: claudebook
Version: 0.1.3
Summary: Add your description here
Author-email: 3956745+thejcannon@users.noreply.github.com
License-File: LICENSE
Requires-Python: >=3.11
Requires-Dist: cyclopts>=4.0.0
Requires-Dist: pyyaml>=6.0.3
